Disc_Hub/__init__.py
Disc_Hub/evaluate.py
Disc_Hub/main.py
Disc_Hub/models.py
Disc_Hub/train.py
Disc_Hub_DIA/__init__.py
Disc_Hub_DIA/evaluate.py
Disc_Hub_DIA/main.py
Disc_Hub_DIA/models.py
Disc_Hub_DIA/train.py
disc_hub_dia-0.2.1.dist-info/METADATA
disc_hub_dia-0.2.1.dist-info/WHEEL
disc_hub_dia-0.2.1.dist-info/top_level.txt
disc_hub_dia-0.2.1.dist-info/RECORD
