Metadata-Version: 2.4
Name: Disc_Hub_DIA
Version: 0.2.1
Summary: A package for Disc Hub Data Integration Analysis
Author: Yiwen Yu
Requires-Dist: numpy
Requires-Dist: matplotlib
Requires-Dist: pandas
Requires-Dist: pyarrow==19.0.0
Requires-Dist: torch>=2.6.0
Requires-Dist: xgboost
Requires-Dist: scikit-learn
Dynamic: author
Dynamic: requires-dist
Dynamic: summary
